{ 
	"coords" : {"lat": 43.80252810897969, "lng": 91.86799458044152, "zoom": 3},
	"RES" : [
		{"id": "JP001", "name": "Sekisui House Ltd. (Japan)", "num": "0", "price": "0", "address":"1-1-88, Oyodonaka, Kita-ku, Osaka, 531-0076, Japan", "web": "https://www.sekisuihouse.co.jp/", "coords": "34.70544245396581, 135.48961166796374", "gob": "no", "score": "4.1", "LE" : {"GY": 0, "GM" : 0, "PO": 0, "GA": 0, "GH": 0} },
		{"id": "JP002", "name": "Daiwa House Industry Co., Ltd. (Japan)", "num": "0", "price": "0", "address":"3-3-5 Umeda, Kita-ku, Osaka 530-8241", "web": "https://www.daiwahouse.com/", "coords": "34.69959352810057, 135.4922834682501", "gob": "no", "score": "3.6", "LE" : {"GY": 0, "GM" : 0, "PO": 0, "GA": 0, "GH": 0} },

		{"id": "SA001", "name": "Red Sea International Company (Saudi Arabia)", "num": "0", "price": "0", "address":"9638 الطريق السريع, King Fahd Industrial Port، رقم 1, Al Jubail 35514, Saudi Arabia", "web": "https://redseaintl.com/", "coords": "27.022260478801137, 49.63928033252702", "gob": "no", "score": "0", "LE" : {"GY": 0, "GM" : 0, "PO": 0, "GA": 0, "GH": 0} },

		{"id": "AU001", "name": "Commod House (Austria)", "num": "0", "price": "0", "address":"Heinrichstraße 4, 8010 Graz, Austria", "web": "https://www.commod-house.com/en/", "coords": "47.078107871677496, 15.444266115340538", "gob": "no", "score": "0", "LE" : {"GY": 0, "GM" : 0, "PO": 0, "GA": 0, "GH": 0} },
		{"id": "AU002", "name": "McCube (Austria)", "num": "0", "price": "0", "address":"Graf-Adolf-Straße 22, 40212 Düsseldorf, Germany", "web": "https://www.mc-cube.at/", "coords": "47.078107871677496, 15.444266115340538", "gob": "no", "score": "0", "LE" : {"GY": 0, "GM" : 0, "PO": 0, "GA": 0, "GH": 0} },

		{"id": "PH001", "name": "Smart House (Pkilipines)", "num": "0", "price": "0", "address":"128 kamuning road , Quezon City, Philippines", "web": "https://www.smarthouseprefab.com.ph/", "coords": "14.630623609660402, 121.04511685394132", "gob": "no", "score": "0", "LE" : {"GY": 0, "GM" : 0, "PO": 0, "GA": 0, "GH": 0} },

		{"id": "CH001", "name": "Gliami (China)", "num": "0", "price": "0", "address":"Dong Shandong Road North,Jiulonggang Town,Datong District Jiulonggang,Huainan City Town,Anhui Province.", "web": "https://glamni.com/", "coords": "32.61294456948655, 117.10129436973642", "gob": "no", "score": "5", "LE" : {"GY": 0, "GM" : 0, "PO": 0, "GA": 0, "GH": 0} },
		{"id": "CN001", "name": "Qingdao Liansheng International Trade Co., Ltd. (China)", "num": "0", "price": "0", "address":"No. 398, Yu Chang Road, ChangLe Industrial Park, WeiFang, Shandong, China.", "web": "https://www.lianshenghouse.com/", "coords": "36.73278455526413, 118.83614145454423", "gob": "no", "score": "0", "LE" : {"GY": 0, "GM" : 0, "PO": 0, "GA": 0, "GH": 0} },
		{"id": "CN001", "name": "Capsule Castle (China)", "num": "0", "price": "0", "address":"Huanglou Town, Qingzhou City, Shandong Province, China", "web": "https://capsulecastle.com/", "coords": "36.64799650868779, 118.606902867938", "gob": "no", "score": "0", "LE" : {"GY": 0, "GM" : 0, "PO": 0, "GA": 0, "GH": 0} }

	],
	"CD": [
	],
	"AM": [
	],
	"AD": [
	]
}
